pdbe/__init__.py
pdbe/cli.py
pdbe/commits.py
pdbe/main.py
pdbe/utils.py
pdbe-0.3.0.dist-info/DESCRIPTION.rst
pdbe-0.3.0.dist-info/METADATA
pdbe-0.3.0.dist-info/RECORD
pdbe-0.3.0.dist-info/WHEEL
pdbe-0.3.0.dist-info/entry_points.txt
pdbe-0.3.0.dist-info/metadata.json
pdbe-0.3.0.dist-info/top_level.txt
tests/__init__.py
tests/test_cli.py
tests/test_utils.py
